modelport/__init__.py
modelport/export_resnet.py
modelport/modelport.py
modelport/cli/__init__.py
modelport/cli/compile.py
modelport/cli/deploy.py
modelport/cli/export.py
modelport/cli/main.py
modelport/cli/run.py
modelport/cli/run_native.py
modelport/compile/__init__.py
modelport/compile/tvm.py
modelport/core/__init__.py
modelport/core/compiler.py
modelport/core/deployer.py
modelport/core/docker_runner.py
modelport/core/exporter.py
modelport/core/model_utils.py
modelport/core/runtime.py
modelport/examples/direct_test.py
modelport/examples/inference.py
modelport/examples/inference_template.py
modelport/examples/multiarch_test.py
modelport/examples/run_all_tests.py
modelport/examples/simple_usage.py
modelport/examples/test_compile.py
modelport/examples/train_resnet18.py
modelport/export/__init__.py
modelport/export/onnx.py
modelport/inference/__init__.py
modelport/inference/runner.py
modelport/runtime/__init__.py
modelport/runtime/templates/__init__.py
modelport/runtime/templates/model_template.json
modelport/utils/__init__.py
modelport/utils/diagnostics.py
model_port-2.0.6.dist-info/LICENSE
model_port-2.0.6.dist-info/METADATA
model_port-2.0.6.dist-info/WHEEL
model_port-2.0.6.dist-info/entry_points.txt
model_port-2.0.6.dist-info/top_level.txt
model_port-2.0.6.dist-info/RECORD
