Metadata-Version: 2.1
Name: model-port
Version: 2.0.6
Summary: Model deployment, portability, and architecture-independent compilation
Author-email: SaiKrishna-KK <your.email@example.com>
License: MIT
Project-URL: Homepage, https://github.com/SaiKrishna-KK/model-port
Project-URL: Bug Tracker, https://github.com/SaiKrishna-KK/model-port/issues
Project-URL: Documentation, https://github.com/SaiKrishna-KK/model-port/blob/main/docs/index.md
Classifier: Development Status :: 4 - Beta
Classifier: Intended Audience :: Developers
Classifier: Intended Audience :: Science/Research
Classifier: Programming Language :: Python :: 3
Classifier: Programming Language :: Python :: 3.8
Classifier: Programming Language :: Python :: 3.9
Classifier: Programming Language :: Python :: 3.10
Classifier: Topic :: Scientific/Engineering :: Artificial Intelligence
Requires-Python: >=3.8
License-File: LICENSE
Requires-Dist: torch>=1.8.0
Requires-Dist: onnx>=1.10.0
Requires-Dist: onnxruntime>=1.8.0
Requires-Dist: numpy>=1.20.0
Requires-Dist: ml-dtypes==0.2.0
Provides-Extra: dev
Requires-Dist: pytest>=7.0.0; extra == "dev"
Requires-Dist: black>=23.0.0; extra == "dev"
Requires-Dist: isort>=5.12.0; extra == "dev"
Provides-Extra: docs
Requires-Dist: sphinx>=6.0.0; extra == "docs"
Requires-Dist: sphinx-rtd-theme>=1.2.0; extra == "docs"
Provides-Extra: gpu
Requires-Dist: onnxruntime-gpu>=1.8.0; extra == "gpu"
Provides-Extra: tvm
